Workbook

Sheet 汇总看板
A1: 仟流智算 2.0｜四大核心逻辑场景测试看板
A2: 共 40 个查验场景。请在“测试总表”回填入口、操作、内容、实际结果和 Evidence；本页自动汇总。
A4: 总场景 | C4: 已测试 | E4: 通过 | G4: 失败/阻塞 | I4: 完成率
A5: =COUNTA(测试总表!$A$5:$A$44) | C5: =COUNTIF(测试总表!$Q$5:$Q$44,"<>未测试") | E5: =COUNTIF(测试总表!$Q$5:$Q$44,"通过") | G5: =COUNTIF(测试总表!$Q$5:$Q$44,"不通过")+COUNTIF(测试总表!$Q$5:$Q$44,"阻塞") | I5: =IFERROR(C5/A5,0)
A8: 核心逻辑 | B8: 总数 | C8: 已测试 | D8: 通过 | E8: 失败/阻塞 | F8: 待确认 | G8: 完成率
A9: 持续生产 | B9: =COUNTIF(测试总表!$B$5:$B$44,A9) | C9: =COUNTIFS(测试总表!$B$5:$B$44,A9,测试总表!$Q$5:$Q$44,"<>未测试") | D9: =COUNTIFS(测试总表!$B$5:$B$44,A9,测试总表!$Q$5:$Q$44,"通过") | E9: =COUNTIFS(测试总表!$B$5:$B$44,A9,测试总表!$Q$5:$Q$44,"不通过")+COUNTIFS(测试总表!$B$5:$B$44,A9,测试总表!$Q$5:$Q$44,"阻塞") | F9: =COUNTIFS(测试总表!$B$5:$B$44,A9,测试总表!$Q$5:$Q$44,"待确认") | G9: =IFERROR(C9/B9,0)
A10: 按量消耗 | B10: =COUNTIF(测试总表!$B$5:$B$44,A10) | C10: =COUNTIFS(测试总表!$B$5:$B$44,A10,测试总表!$Q$5:$Q$44,"<>未测试") | D10: =COUNTIFS(测试总表!$B$5:$B$44,A10,测试总表!$Q$5:$Q$44,"通过") | E10: =COUNTIFS(测试总表!$B$5:$B$44,A10,测试总表!$Q$5:$Q$44,"不通过")+COUNTIFS(测试总表!$B$5:$B$44,A10,测试总表!$Q$5:$Q$44,"阻塞") | F10: =COUNTIFS(测试总表!$B$5:$B$44,A10,测试总表!$Q$5:$Q$44,"待确认") | G10: =IFERROR(C10/B10,0)
A11: 峰谷差异 | B11: =COUNTIF(测试总表!$B$5:$B$44,A11) | C11: =COUNTIFS(测试总表!$B$5:$B$44,A11,测试总表!$Q$5:$Q$44,"<>未测试") | D11: =COUNTIFS(测试总表!$B$5:$B$44,A11,测试总表!$Q$5:$Q$44,"通过") | E11: =COUNTIFS(测试总表!$B$5:$B$44,A11,测试总表!$Q$5:$Q$44,"不通过")+COUNTIFS(测试总表!$B$5:$B$44,A11,测试总表!$Q$5:$Q$44,"阻塞") | F11: =COUNTIFS(测试总表!$B$5:$B$44,A11,测试总表!$Q$5:$Q$44,"待确认") | G11: =IFERROR(C11/B11,0)
A12: 计量和调度 | B12: =COUNTIF(测试总表!$B$5:$B$44,A12) | C12: =COUNTIFS(测试总表!$B$5:$B$44,A12,测试总表!$Q$5:$Q$44,"<>未测试") | D12: =COUNTIFS(测试总表!$B$5:$B$44,A12,测试总表!$Q$5:$Q$44,"通过") | E12: =COUNTIFS(测试总表!$B$5:$B$44,A12,测试总表!$Q$5:$Q$44,"不通过")+COUNTIFS(测试总表!$B$5:$B$44,A12,测试总表!$Q$5:$Q$44,"阻塞") | F12: =COUNTIFS(测试总表!$B$5:$B$44,A12,测试总表!$Q$5:$Q$44,"待确认") | G12: =IFERROR(C12/B12,0)
A15: 问题类型 | D15: 未关闭高优先级
A16: 数据缺口 | B16: =COUNTIF(测试总表!$P$5:$P$44,A16) | D16: P0/P1 且未通过 | E16: =COUNTIFS(测试总表!$R$5:$R$44,"P0",测试总表!$Q$5:$Q$44,"<>通过")+COUNTIFS(测试总表!$R$5:$R$44,"P1",测试总表!$Q$5:$Q$44,"<>通过")
A17: 解释缺口 | B17: =COUNTIF(测试总表!$P$5:$P$44,A17)
A18: 闭环缺口 | B18: =COUNTIF(测试总表!$P$5:$P$44,A18)
A19: 口径错误 | B19: =COUNTIF(测试总表!$P$5:$P$44,A19)
A20: 严重错误 | B20: =COUNTIF(测试总表!$P$5:$P$44,A20)

Sheet 测试总表
A1: 仟流智算 2.0｜四大核心逻辑场景测试总表
A2: 填写顺序：找到页面/入口 → 执行操作 → 判断是否有真实内容 → 记录实际结果 → 选择问题类型、结论和严重级别 → 附截图或 Evidence。
A3: 测试范围：本表只按已部署的仟流智算 2.0 页面、菜单和真实数据测试；不要求切换版本或寻找其他菜单。凭证失效、熔断、超时、并发抢额度等场景只能使用测试主体/测试资源、历史事件或测试环境。
A4: 测试编号 | B4: 核心逻辑 | C4: 客户核心问题 | D4: 场景 | E4: 测试方式 | F4: 查验问题 | G4: 建议测试动作 | H4: 重点查验 | I4: 预期结果/通过标准 | J4: 实际页面/入口 | K4: 入口是否存在 | L4: 操作是否可用 | M4: 页面是否有内容 | N4: 内容是否真实/非演示 | O4: 实际结果记录 | P4: 问题类型 | Q4: 测试结论 | R4: 严重级别 | S4: 问题描述 | T4: 截图/Evidence | U4: 测试人 | V4: 测试日期 | W4: 复测结论 | X4: 备注
A5: CP-01 | B5: 持续生产 | C5: 现在还能不能用？还能用多久？ | D5: 全部资源正常 | E5: 真实请求 | F5: 系统现在是否真的可用？ | G5: 选择一个已授权员工，分别对当前主资源发起一次低风险真实请求；对照首页、厂商资源和请求明细。 | H5: 资源健康、最近检测时间、成功率、请求状态与实际返回。 | I5: 请求成功；首页、资源页和请求明细状态一致；数据时间有效。 | J5: 运行保障；厂商资源 → 资源健康与异常；用量账本 → 请求明细 | K5: 是 | L5: 是 | M5: 有 | N5: 是 | O5: 运行保障显示活跃熔断 0、受阻资源 0、影响请求 0、降级资源 0、下次自动恢复暂无；Kimi、DeepSeek、智谱资源健康均显示正常，调度影响为正常参与调度，可用性为允许请求，状态原因为恢复正常、无需处置；用量账本请求明细存在真实请求记录，包含请求 ID、发起主体、模型、厂商/资源、输入 Token 和输出 Token。 | P5: 通过 | Q5: 通过 | R5: 未分级 | T5: /var/folders/bd/x5tqktw96l5cw5r90mvnbty80000gp/T/codex-clipboard-6014863e-60ab-4fa9-8943-67902ab42bc1.png; /var/folders/bd/x5tqktw96l5cw5r90mvnbty80000gp/T/codex-clipboard-db3e5989-b12d-40cd-829a-8bfdd2b47501.png; /var/folders/bd/x5tqktw96l5cw5r90mvnbty80000gp/T/codex-clipboard-05143320-5614-48c1-882b-0020afe2db26.png | V5: 2026-08-18 | W5: 未复测 | X5: CP-01 已通过；CP-02 的经营数据新鲜度问题单独记录。
A6: CP-02 | B6: 持续生产 | C6: 现在还能不能用？还能用多久？ | D6: API 余额逐渐降低 | E6: 页面观察 | F6: 这笔余额还能支撑多久？ | G6: 打开 API 资源详情和供给预测，记录余额、1h/24h/7d 速度、覆盖时长及预计耗尽。 | H6: 金额余额与 Token 必须分栏；预测来源、数据时间和可信度。 | I6: 显示金额余额、消耗速度、覆盖时长和预计耗尽；不得把人民币余额伪换算为 Token。 | J6: 厂商资源 → DeepSeek-仟流智算 → 更新经营数据 | K6: 是 | L6: 是 | M6: 有 | N6: 是 | O6: 充值 109.41 CNY；当前余额 68.00 CNY；本期实际费用 47.41 CNY；余额更新时间 2026-08-03 11:58（距测试日约 15 天）；累计费用和费用周期结束为空。供给预测仍显示预计耗尽、覆盖时长和 MEDIUM 可信度，但经营快照未按当前测试日更新。 | P6: 数据缺口 | Q6: 待确认 | R6: P1 | T6: /var/folders/bd/x5tqktw96l5cw5r90mvnbty80000gp/T/codex-clipboard-9d28a214-4e6e-4bb2-9e6d-a02d7918d0a7.png; /var/folders/bd/x5tqktw96l5cw5r90mvnbty80000gp/T/codex-clipboard-1e8d22f9-2282-4daf-a615-ef4bd2bc28e9.png | V6: 2026-08-18 | W6: 未复测 | X6: 建议进入 2.0 后续改进：按资源每日自动同步余额/费用，保留快照、数据时间、同步状态和失败原因。
A7: CP-03 | B7: 持续生产 | C7: 现在还能不能用？还能用多久？ | D7: 突然出现消耗高峰 | E7: 数据对账 | F7: 消耗加速后，原预测是否及时变化？ | G7: 选择一个已出现峰值的历史时段，对比峰值前后 1h/24h/7d 速度和耗尽预测。 | H7: 峰值识别、预测更新时间、旧预测是否被替换。 | I7: 消耗速度变化后覆盖时长与耗尽预测同步调整；旧预测不冒充当前预测。 | J7: 厂商资源 → 供给预测 | K7: 是 | L7: 不适用 | M7: 有 | N7: 是 | O7: 供给预测为只读展示：DeepSeek 1h/24h/7d 为 — / 0.04101473 / 0.05282199，预计耗尽 2026-10-19 16:46:30，覆盖约 1486.74067724h，可信度 MEDIUM；智谱为 — / — / 249948.37068039，预计耗尽 2026-09-19 07:14:21，下一恢复 2026-08-26 12:00:00，覆盖约 757.20479187h，可信度 MEDIUM；Kimi 为 29422 / 2137116.75834274 / 506080.39035205，预计耗尽 2026-08-19 11:49:00，下一恢复 2026-08-20 11:49:00，覆盖约 34.38129819h，可信度 HIGH。页面无交互刷新或历史对比。 | P7: 未测试 | Q7: 待确认 | R7: 未分级 | T7: /var/folders/bd/x5tqktw96l5cw5r90mvnbty80000gp/T/codex-clipboard-bfada8b8-a46b-428b-b3f3-0d68b08f6e25.png | V7: 2026-08-18 | W7: 未复测 | X7: 只验证展示内容；自动同步与数据新鲜度归入 POOL20-025。
A8: CP-04 | B8: 持续生产 | C8: 现在还能不能用？还能用多久？ | D8: Coding Plan 五小时额度接近耗尽 | E8: 页面观察 | F8: 当前五小时窗口还能不能继续使用？ | G8: 打开 Kimi/智谱 Coding Plan 的原生额度窗口，查看五小时已用、剩余、利用率和重置时间。 | H8: 五小时窗口必须独立展示；同步状态和数据时间。 | I8: 显示五小时已用、剩余、利用率、重置时间和同步状态；不能只显示本地 Token。 | J8: 厂商资源 → 厂商额度窗口 | K8: 是 | L8: 是 | M8: 有 | N8: 是 | O8: Kimi 与智谱额度窗口均为厂商提供数据。Kimi：滚动 5 小时已用 5/100、剩余 95、重置 2026-08-18 20:16:04；周额度已用 17/100、剩余 83、重置 2026-08-24 11:16:04；同步成功，数据截至 2026-08-18 18:02:35，来源 PROVIDER_SYNC/pool032-v1。DeepSeek：API 计费，厂商窗口不适用。智谱：已手动执行同步后，滚动 5 小时仍显示已用 0/100、剩余 100，但没有显示重置时间；周额度已用 1/100、剩余 99、重置 2026-08-21 17:23:09。 | P8: 数据缺口 | Q8: 待确认 | R8: 未分级 | T8: /var/folders/bd/x5tqktw96l5cw5r90mvnbty80000gp/T/codex-clipboard-ab74f81b-d1f4-45f7-8e82-fb188186f4be.png | V8: 2026-08-18 | W8: 未复测 | X8: 已确认 Kimi/智谱窗口均来自厂商；智谱手动同步后五小时重置时间仍未显示。下一步核对同步原始响应、适配层字段和前端映射，不预判原因。
A9: CP-05 | B9: 持续生产 | C9: 现在还能不能用？还能用多久？ | D9: Coding Plan 周额度接近耗尽 | E9: 页面观察 | F9: 本周剩余额度是否够用？ | G9: 打开 Kimi/智谱周额度窗口，并与五小时窗口同时核对。 | H9: 周窗口和五小时窗口不能合并；厂商原生口径。 | I9: 周额度、剩余、利用率和重置时间独立正确展示，并标明数据来源。 | J9: 厂商资源 → 厂商额度窗口 | K9: 是 | L9: 不适用 | M9: 有 | N9: 是 | O9: Kimi 周额度已用 17/100、剩余 83、重置 2026-08-24 11:16:04；智谱周额度已用 1/100、剩余 99、重置 2026-08-21 17:23:09；两者均显示同步成功。DeepSeek 为 API 计费资源，厂商周窗口不适用。当前值不在临界耗尽区间。 | P9: 通过 | Q9: 通过 | R9: 未分级 | T9: /var/folders/bd/x5tqktw96l5cw5r90mvnbty80000gp/T/codex-clipboard-ab74f81b-d1f4-45f7-8e82-fb188186f4be.png | V9: 2026-08-18 | W9: 未复测 | X9: 本条只验收周额度展示，不点击立即同步。
A10: CP-06 | B10: 持续生产 | C10: 现在还能不能用？还能用多久？ | D10: Provider Key 失效或凭证异常 | E10: 历史事件/测试环境 | F10: 为什么资源突然不可用？ | G10: 只在测试资源制造无效凭证，或查看既有凭证异常事件；禁止在生产主资源修改 Key。 | H10: 异常原因、失败证据、调度影响、Secret 脱敏和恢复入口。 | I10: 资源健康显示凭证异常及影响；不暴露完整 Secret；存在更新凭证或恢复入口。 | J10: 厂商资源 → 资源健康与异常 | K10: 是 | L10: 不适用 | M10: 有 | N10: 是 | O10: 当前 Kimi、DeepSeek、智谱均显示正常；调度影响为正常参与调度；可用性为允许请求；状态原因为恢复正常；恢复说明为资源健康、无需处置。当前没有可观察的凭证失效、连接失败或认证异常事件。 | P10: 未测试 | Q10: 未测试 | R10: 未分级 | T10: /var/folders/bd/x5tqktw96l5cw5r90mvnbty80000gp/T/codex-clipboard-e9956f33-5dd5-4d6c-81ce-26ac32e1793b.png | V10: 2026-08-18 | W10: 未复测 | X10: 没有异常样本，不在生产人为制造凭证故障。
A11: CP-07 | B11: 持续生产 | C11: 现在还能不能用？还能用多久？ | D11: 主资源连续失败并熔断 | E11: 历史事件/测试环境 | F11: 业务有没有中断？ | G11: 使用既有熔断事件，或在测试资源受控触发连续失败，观察备用资源切换。 | H11: 触发信号、影响请求、备用资源、恢复时间和请求证据。 | I11: 熔断事件可解释；新请求切到可用备用资源；请求明细可看到真实切换。 | J11: 运行保障 → 熔断事件；运行保障 → 可用性规则 | K11: 是 | L11: 不适用 | M11: 有 | N11: 是 | O11: 熔断事件页已勾选“显示历史事件”，但当前没有熔断事件。可用性规则页有新建草稿表单（上游信号、额度耗尽、硬熔断、固定 10 分钟），当前未看到已发布生效规则，因此没有可触发的熔断事件。 | P11: 未测试 | Q11: 未测试 | R11: 未分级 | T11: /var/folders/bd/x5tqktw96l5cw5r90mvnbty80000gp/T/codex-clipboard-682eb686-3ada-453f-86e4-f32ce43b2c9c.png; /var/folders/bd/x5tqktw96l5cw5r90mvnbty80000gp/T/codex-clipboard-ec822513-ce98-49eb-b05b-3b8d38566286.png | V11: 2026-08-18 | W11: 未复测 | X11: 熔断事件依赖已发布可用性规则；未在生产创建或发布规则。
A12: CP-08 | B12: 持续生产 | C12: 现在还能不能用？还能用多久？ | D12: 厂商恢复正常 | E12: 历史事件/测试环境 | F12: 系统什么时候重新使用原资源？ | G12: 对照一次已恢复事件，或在测试资源恢复后执行探测与新请求。 | H12: 自动/人工恢复、探测结果、恢复时间、候选集恢复。 | I12: 恢复记录完整；探测通过后新请求重新进入候选；历史请求不被改写。 | J12: 运行保障 → 异常中心 | K12: 是 | L12: 不适用 | M12: 有 | N12: 是 | O12: 异常中心存在多条“运行保障预警 · AUTO_RESOLVED”，原因包括上游技术故障、上游配置错误；同时存在“主体额度使用异常 · OPEN”（额度使用率 119.8%，超额 1971477）。AUTO_RESOLVED 卡片不能展开，无法查看事件时间、恢复时间、影响资源、影响请求和恢复后放行结果。 | P12: 解释缺口 | Q12: 待确认 | R12: 未分级 | T12: /var/folders/bd/x5tqktw96l5cw5r90mvnbty80000gp/T/codex-clipboard-7b4db767-873b-4b2d-9cbe-6010c4270001.png | V12: 2026-08-18 | W12: 未复测 | X12: 有恢复状态，但缺少恢复过程与证据下钻。不要点击“标记已处理”。
A13: CP-09 | B13: 持续生产 | C13: 现在还能不能用？还能用多久？ | D13: 厂商数据长时间未同步 | E13: 页面观察 | F13: 页面剩余额度还能相信吗？ | G13: 查找一个过期快照或断开测试同步源，查看资源利用和供给预测。 | H13: STALE/不可计算、数据时间、原因；不得伪造 0 或精确日期。 | I13: 明确显示数据过期或不可计算及原因；不显示虚假 0%、余额或耗尽日期。 | J13: 厂商资源 → 资源利用事实 | K13: 是 | L13: 不适用 | M13: 有 | N13: 是 | O13: Kimi、智谱的利用依据显示 CODING_PLAN_WEEKLY_STALE；DeepSeek 显示 MONTHLY_BUDGET_NOT_CONFIGURED，且数据时间可见。未知分母、窗口过期和预算未设置均没有伪造成 0%，并保留相应说明。 | P13: 通过 | Q13: 通过 | R13: 未分级 | T13: /var/folders/bd/x5tqktw96l5cw5r90mvnbty80000gp/T/codex-clipboard-9eeea186-7c57-48ed-ab1f-08ceadb4e54e.png | V13: 2026-08-18 | W13: 未复测 | X13: 本条通过展示层核验；自动同步新鲜度问题另记 POOL20-025。
A14: CP-10 | B14: 持续生产 | C14: 现在还能不能用？还能用多久？ | D14: 某项资源连续多天没有请求 | E14: 页面观察 | F14: 这个资源是不是买闲了？ | G14: 打开资源利用概况和采购复盘，选择最近无请求的资源。 | H14: 最近使用、连续无调用天数、利用率、自动闲置结论和页面一致性。 | I14: 展示最近使用与连续无调用天数；未冻结阈值时显示“未判定”；采购复盘一致。 | J14: 厂商资源 → 资源利用事实 | K14: 是 | L14: 不适用 | M14: 有 | N14: 是 | O14: 页面展示最近使用时间和连续无调用天数：Kimi 0 天、DeepSeek 0 天、智谱 1 天；闲置状态显示“未判定”，没有仅因 Token 少自动断言闲置。当前样本没有连续多日无调用资源，未覆盖长期闲置样本。 | P14: 未测试 | Q14: 待确认 | R14: 未分级 | T14: /var/folders/bd/x5tqktw96l5cw5r90mvnbty80000gp/T/codex-clipboard-9eeea186-7c57-48ed-ab1f-08ceadb4e54e.png | V14: 2026-08-18 | W14: 未复测 | X14: 字段展示通过；当前没有多日无调用样本，不能完成长期闲置行为验证。
A15: UC-01 | B15: 按量消耗 | C15: 谁用了？用了多少？用在哪里？ | D15: 查看单个员工本日用量 | E15: 真实请求/数据对账 | F15: 李佳今天具体用了多少？ | G15: 在用量概览选择一个员工和“今日”，再下钻请求明细。 | H15: 请求数、输入、输出、真实 Token、费用、趋势和筛选范围。 | I15: 只统计该员工今日数据；趋势与请求明细汇总守恒。 | J15: 用量账本 → 用量概览；请求明细 | K15: 是 | L15: 是 | M15: 有 | N15: 是 | O15: 李佳今日（2026-08-18）活跃主体 1、请求 3、真实 Token 29,422、API ¥0.00、套餐扣减 29,422；独立请求明细按主体和 2026-08-18 12:49～18:49 筛选后共 3 条，输入 28,607+435+87，输出 183+64+46，扣减 28,790+499+133，合计真实 Token 29,422。 | P15: 通过 | Q15: 通过 | R15: 未分级 | T15: /var/folders/bd/x5tqktw96l5cw5r90mvnbty80000gp/T/codex-clipboard-89202030-b976-48c3-83a7-220fbd8e2411.png; /var/folders/bd/x5tqktw96l5cw5r90mvnbty80000gp/T/codex-clipboard-419af6e3-705e-4792-a7b7-0d8e32518c30.png | V15: 2026-08-18 | W15: 未复测 | X15: 请求明细是独立页，按自身时间筛选核验，不要求自动继承概览日期。
A16: UC-02 | B16: 按量消耗 | C16: 谁用了？用了多少？用在哪里？ | D16: 查看单个员工一周用量 | E16: 数据对账 | F16: 该员工周一到周日每天用了多少？ | G16: 选择单个员工和“本周”，逐日记录七天数据并汇总。 | H16: 周一至周日边界、七天趋势、总量和请求下钻。 | I16: 七天趋势之和等于本周总量；不混入其他员工；可进入请求明细。 | J16: 用量账本 → 用量概览；请求明细 | K16: 是 | L16: 是 | M16: 有 | N16: 是 | O16: 李佳本周（2026-08-17～2026-08-24）请求 258、真实 Token 13,493,147、API ¥0.00、套餐扣减 13,493,147；趋势周一 13,463,725、周二 29,422，合计一致。请求明细按周范围显示 258 条、13 页；明细页以逐条请求为主，不要求显示筛选结果 Token 总计。 | P16: 通过 | Q16: 通过 | R16: 未分级 | T16: /var/folders/bd/x5tqktw96l5cw5r90mvnbty80000gp/T/codex-clipboard-41aef76f-8936-4060-88ca-6b124af0a2e6.png; /var/folders/bd/x5tqktw96l5cw5r90mvnbty80000gp/T/codex-clipboard-ec87f106-3b13-4377-8b09-a2b7e53b677b.png | V16: 2026-08-18 | W16: 未复测 | X16: 未来日期没有数据属于正常；请求明细按独立页的条数和逐行数据核验。
... A31: PV-07 | B31: 峰谷差异 | C31: 什么时候使用更划算？ | D31: Coding Plan 当前窗口仍有额度 | E31: 请求下钻 | F31: 此时应该优先套餐还是 API？ | G31: 选择套餐窗口有剩余且 API 也可用的模型，查看候选和实际调度。 | H31: 套餐窗口、恢复周期、候选资源、实际选择与理由。 | I31: 实际选择能够用已展示事实解释；不以本地 Token 冒充厂商窗口。 | J31: 用量账本 → 请求明细 → 请求展开 | K31: 是 | L31: 是 | M31: 有 | N31: 是 | O31: Kimi 请求使用 Coding Plan，套餐内、扣减 95,913、API 费用为套餐内；路由候选只有一个，调度为 ALLOW_NO_POLICY，无法证明套餐优先策略。 | P31: 未测试 | Q31: 待确认 | R31: 未分级 | T31: /var/folders/bd/x5tqktw96l5cw5r90mvnbty80000gp/T/codex-clipboard-30ad18fe-4338-45f5-bafa-fb1314bbfcc5.png | V31: 2026-08-18 | W31: 未复测 | X31: 套餐实际使用已证实，套餐优先尚无多候选样本。
A32: PV-08 | B32: 峰谷差异 | C32: 什么时候使用更划算？ | D32: Coding Plan 窗口耗尽 | E32: 历史事件/测试环境 | F32: 继续等待还是切换收费 API？ | G32: 使用既有耗尽事件，或在测试资源模拟窗口耗尽后发起请求。 | H32: 恢复时间、备用 API 成本、切换动作与业务时效。 | I32: 系统显示等待与切换事实；实际动作和理由可追溯。 | J32: 厂商资源 → 厂商额度窗口；请求明细 | K32: 是 | L32: 不适用 | M32: 有 | N32: 无法判断 | O32: 当前没有 Coding Plan 额度耗尽样本，无法验证等待重置或用户自行切换。 | P32: 未测试 | Q32: 待确认 | R32: 未分级 | V32: 2026-08-18 | W32: 未复测 | X32: 额度耗尽提示口径已记录 POOL20-033。
A33: PV-09 | B33: 峰谷差异 | C33: 什么时候使用更划算？ | D33: 首页显示调度节省 | E33: 数据对账 | F33: 到底节省了多少钱？ | G33: 选择一笔或一段有“调度节省”的数据，复算比较基线和实际成本。 | H33: 比较基线、基准成本、实际成本、公式与数据来源。 | I33: 节省金额可复算；没有可靠基线时显示不可计算，而不是伪造数字。 | J33: 首页；请求明细 | K33: 是 | L33: 不适用 | M33: 有 | N33: 是 | O33: 首页本月调度节省显示 0.00；当前未观察到可计算的实际 SWITCH。 | P33: 未测试 | Q33: 待确认 | R33: 未分级 | T33: /var/folders/bd/x5tqktw96l5cw5r90mvnbty80000gp/T/codex-clipboard-d939c1c4-eb1f-4fd6-8ee1-cf20b9ef08fe.png | V33: 2026-08-18 | W33: 未复测 | X33: 调度节省算法已进入 POOL20-035 讨论。
A34: PV-10 | B34: 峰谷差异 | C34: 什么时候使用更划算？ | D34: 最便宜资源延迟高或不可用 | E34: 请求下钻 | F34: 便宜资源是不是一定值得用？ | G34: 选择最低价资源不健康或高延迟的请求，查看候选淘汰和最终选择。 | H34: 价格、健康、延迟、失败率、额度和业务影响。 | I34: 调度理由能解释为何放弃最低价资源；机会成本有事实支撑。 | J34: 用量账本 → 请求明细 → 路由候选 | K34: 是 | L34: 不适用 | M34: 有 | N34: 是 | O34: 当前抽查成功请求大多只有一个候选；没有多候选价格/可用性取舍样本。 | P34: 未测试 | Q34: 待确认 | R34: 未分级 | T34: /var/folders/bd/x5tqktw96l5cw5r90mvnbty80000gp/T/codex-clipboard-c7ec2b5a-c9b2-436a-8f56-cd1c98dcc2a8.png | V34: 2026-08-18 | W34: 未复测 | X34: 系统只记录事实，不自动判断便宜资源一定更好。
A35: MD-01 | B35: 计量和调度 | C35: 为什么这次放行、切换或拒绝？ | D35: 无效、撤销或停用的 Key | E35: 测试主体 | F35: 为什么请求被拒绝？ | G35: 使用专用测试主体的无效/撤销 Key 发起请求；禁止使用生产主账号。 | H35: 门禁阶段、主体/Key 状态、上游未调用、无伪 Attempt/费用。 | I35: 请求在上游前被拒绝；错误原因明确；不产生实际费用。 | J35: 用量账本 → 请求明细 | K35: 是 | L35: 不适用 | M35: 有 | N35: 是 | O35: 失败请求共 260 条，当前直接检查到 CLIENT_INVALID、UPSTREAM_TEMPORARY、STREAM_INTERRUPTED_AFTER_COMMIT；未观察到 403 或授权类错误。 | P35: 未测试 | Q35: 未测试 | R35: 未分级 | V35: 2026-08-18 | W35: 未复测 | X35: 当前无 403/授权错误样本。
A36: MD-02 | B36: 计量和调度 | C36: 为什么这次放行、切换或拒绝？ | D36: 员工没有目标模型授权 | E36: 测试主体 | F36: 为什么有额度也不能用？ | G36: 对未授权目标模型的测试主体发起请求。 | H36: Grant、模型授权、门禁位置和审计。 | I36: 缺少授权时上游前拒绝，并给出稳定原因；有受控审计记录。 | J36: 批量模型授权；用量账本 → 请求明细 | K36: 是 | L36: 不适用 | M36: 有 | N36: 是 | O36: 当前没有观察到 principal_grant_required、模型未授权或授权过期请求。 | P36: 未测试 | Q36: 未测试 | R36: 未分级 | V36: 2026-08-18 | W36: 未复测 | X36: 不人为停用授权制造故障。
A37: MD-03 | B37: 计量和调度 | C37: 为什么这次放行、切换或拒绝？ | D37: 主体额度不足 | E37: 测试主体 | F37: 为什么被拒绝或按倍率扣减？ | G37: 给测试主体配置临界额度，分别测试拒绝、允许超额或倍率策略。 | H37: 请求额度、剩余额度、超额策略、倍率和最终扣减。 | I37: 行为与生效规则一致；余额不为负；原因可解释。 | J37: 用量账本 → 请求明细；额度规则 | K37: 是 | L37: 不适用 | M37: 有 | N37: 是 | O37: 失败请求中未发现 REJECT_EXHAUSTED；直接检查到智谱失败请求剩余额度比例约 63.09%，不是额度耗尽。 | P37: 未测试 | Q37: 未测试 | R37: 未分级 | V37: 2026-08-18 | W37: 未复测 | X37: 当前没有主体额度不足样本。
A38: MD-04 | B38: 计量和调度 | C38: 为什么这次放行、切换或拒绝？ | D38: 多个资源支持同一模型 | E38: 请求下钻 | F38: 哪些资源进入候选集合？ | G38: 发起一笔拥有多个候选资源的模型请求，展开路由证据。 | H38: 候选全集、优先级、授权/健康/额度/模型排除原因。 | I38: 全部候选及淘汰原因可见；最终选择与策略一致。 | J38: 用量账本 → 请求明细 → 路由候选 | K38: 是 | L38: 不适用 | M38: 有 | N38: 是 | O38: 当前抽查的成功请求路由候选大多只有一个，没有多候选竞争或切换样本。 | P38: 未测试 | Q38: 待确认 | R38: 未分级 | V38: 2026-08-18 | W38: 未复测 | X38: 多候选路由场景待测试夹具。
A39: MD-05 | B39: 计量和调度 | C39: 为什么这次放行、切换或拒绝？ | D39: 第一候选正常成功 | E39: 真实请求 | F39: 为什么最终选择这个资源？ | G39: 发起一笔正常请求，完整展开调度、Attempt 和结算。 | H39: 调度策略版本、资源、模型、价格/倍率快照、Settlement。 | I39: 一次成功 Attempt 和一个最终 Settlement；选择理由完整。 | J39: 用量账本 → 请求明细 → 请求展开 | K39: 是 | L39: 是 | M39: 有 | N39: 是 | O39: 成功请求可看到 HTTP 200、Attempt 1、结算 SETTLED、Usage、价格规则和 API 成本。 | P39: 通过 | Q39: 通过 | R39: 未分级 | T39: /var/folders/bd/x5tqktw96l5cw5r90mvnbty80000gp/T/codex-clipboard-c7ec2b5a-c9b2-436a-8f56-cd1c98dcc2a8.png | V39: 2026-08-18 | W39: 未复测 | X39: 正常主候选成功链路完整。
A40: MD-06 | B40: 计量和调度 | C40: 为什么这次放行、切换或拒绝？ | D40: 第一候选失败、第二候选成功 | E40: 历史事件/测试环境 | F40: 为什么发生切换？ | G40: 使用既有失败切换请求，或在测试资源受控制造首候选失败。 | H40: 第一 Attempt 失败、第二候选理由、实际用量和最终结算。 | I40: 多 Attempt 如实记录；请求最终只结算一次；切换原因可追溯。 | J40: 用量账本 → 请求明细 | K40: 是 | L40: 不适用 | M40: 有 | N40: 是 | O40: 当前未发现首候选失败后第二候选成功的多 Attempt 切换样本。 | P40: 未测试 | Q40: 待确认 | R40: 未分级 | V40: 2026-08-18 | W40: 未复测 | X40: 当前无法验证故障切换。
A41: MD-07 | B41: 计量和调度 | C41: 为什么这次放行、切换或拒绝？ | D41: 请求超时后重试 | E41: 历史事件/测试环境 | F41: 有没有重复扣费？ | G41: 选择既有超时重试请求，或在测试环境受控触发超时。 | H41: Attempt、预占释放、实际用量、Ledger 和单一 Settlement。 | I41: 实际消耗逐 Attempt 记录；预占正确处理；没有请求级重复结算。 | J41: 用量账本 → 请求明细 | K41: 是 | L41: 不适用 | M41: 有 | N41: 是 | O41: 当前失败样本多为单 Attempt；未发现超时重试后多 Attempt 汇总样本。 | P41: 未测试 | Q41: 待确认 | R41: 未分级 | V41: 2026-08-18 | W41: 未复测 | X41: 当前无法验证重试防重复结算。
A42: MD-08 | B42: 计量和调度 | C42: 为什么这次放行、切换或拒绝？ | D42: 资源处于熔断状态 | E42: 历史事件/测试环境 | F42: 为什么它没有进入候选？ | G42: 查看熔断期间的一笔请求及对应熔断事件。 | H42: 候选排除、事件 ID、恢复时间、备用资源。 | I42: 熔断资源明确被排除；请求、事件和备用切换可关联。 | J42: 运行保障 → 熔断事件；用量账本 → 请求明细 | K42: 是 | L42: 不适用 | M42: 有 | N42: 是 | O42: 运行态势活跃熔断 0，熔断事件显示历史事件为空；无熔断阻断请求样本。 | P42: 未测试 | Q42: 待确认 | R42: 未分级 | T42: /var/folders/bd/x5tqktw96l5cw5r90mvnbty80000gp/T/codex-clipboard-682eb686-3ada-453f-86e4-f32ce43b2c9c.png | V42: 2026-08-18 | W42: 未复测 | X42: 当前无法验证熔断排除候选。
A43: MD-09 | B43: 计量和调度 | C43: 为什么这次放行、切换或拒绝？ | D43: 并发请求抢最后额度 | E43: 测试环境并发 | F43: 会不会出现超卖或负额度？ | G43: 仅在测试环境对临界额度主体并发发起多笔请求。 | H43: 原子预占、允许数量、拒绝数量、余额、释放和结算。 | I43: 没有负额度、超卖、重复释放或重复结算；拒绝原因稳定。 | J43: 用量账本 → 请求明细 → 只看超额 | K43: 是 | L43: 不适用 | M43: 有 | N43: 是 | O43: 只看超额返回 625 条；抽查请求输入 417,186、输出 116、扣减 417,302、成功、Attempt 1、SETTLED，无负额度；但无法证明并发抢最后额度。 | P43: 未测试 | Q43: 待确认 | R43: 未分级 | V43: 2026-08-18 | W43: 未复测 | X43: 超额处理有样本，并发竞争尚无证据。
A44: MD-10 | B44: 计量和调度 | C44: 为什么这次放行、切换或拒绝？ | D44: 单次请求完整追责 | E44: 请求下钻 | F44: 能否完整解释这次请求？ | G44: 随机选择一笔成功和一笔失败请求，从请求 ID 逐层下钻。 | H44: 主体/Key→授权→额度→候选→调度→Attempt→Usage→Ledger→Settlement。 | I44: 证据链完整、字段可关联、历史规则版本不被后来变更覆盖。 | J44: 用量账本 → 请求明细 → 请求展开 | K44: 是 | L44: 部分 | M44: 有 | N44: 是 | O44: 请求详情包含请求、结算、路由候选、上游 Attempt、调度决策和计价证据；调度输入原始 JSON 溢出，计价规则未独立展示。 | P44: 解释缺口 | Q44: 待确认 | R44: P1 | T44: /var/folders/bd/x5tqktw96l5cw5r90mvnbty80000gp/T/codex-clipboard-d1bd2179-61b6-49de-a1fd-51bf56d28d37.png | V44: 2026-08-18 | W44: 未复测 | X44: POOL20-031/032：计价决策和调度输入展示需重排。

Sheet 测试说明
A1: 测试说明与判定口径
A3: 本表只按已部署的仟流智算 2.0 页面、菜单和真实数据测试。每个场景都按：当前事实 → 发生原因 → 系统动作 → 执行结果 → 下钻证据 进行检查。
A5: 核心逻辑 | B5: 客户核心问题 | C5: 重点关注 | D5: 场景数 | E5: 编号范围 | F5: 说明
A6: 持续生产 | B6: 现在还能不能用？还能用多久？ | C6: 可用性、供给余量、消耗速度、耗尽预测、恢复时间、数据新鲜度 | D6: 10 | E6: CP-01～CP-10 | F6: 回答资源能否持续供给。
A7: 按量消耗 | B7: 谁用了？用了多少？用在哪里？ | C7: 主体归属、请求/Token/费用、员工/项目/部门守恒、历史不可变 | D7: 10 | E7: UC-01～UC-10 | F7: 回答成本和责任归属。
A8: 峰谷差异 | B8: 什么时候使用更划算？ | C8: 时间规则、倍率版本、真实节省、机会成本、套餐窗口 | D8: 10 | E8: PV-01～PV-10 | F8: 回答使用时机和经济性。
A9: 计量和调度 | B9: 为什么放行、切换或拒绝？ | C9: 门禁、候选集、调度策略、Attempt、Usage、Ledger、Settlement | D9: 10 | E9: MD-01～MD-10 | F9: 回答每次决策的完整证据链。
A12: 问题类型
A13: 通过 | B13: 事实、原因、动作和证据全部闭环。
A14: 数据缺口 | B14: 页面存在，但数据未知、过期、不可计算或没有真实内容。
A15: 解释缺口 | B15: 结果可能正确，但无法解释为什么放行、切换、拒绝、扣费或归集。
A16: 闭环缺口 | B16: 能发现问题，但没有恢复、调整、处理或下钻入口。
A17: 口径错误 | B17: 页面间数字不一致、Token 重复、成本重复归集或时间边界错误。
A18: 严重错误 | B18: 错误放行、重复扣费、负额度、历史账改写、不可用资源仍显示正常。
A21: 建议测试顺序
A22: 1. 先做页面观察和数据对账，不制造故障。
A23: 2. 再用专用测试主体执行真实请求、门禁、额度和路由测试。
A24: 3. 熔断、凭证失效、超时和并发场景只在测试环境或通过历史事件核验。
A25: 4. 每个“不通过/阻塞”必须附问题描述和截图/Evidence；P0/P1 优先复测。
A28: 依据文件
A29: 仟流智算 2.0 PRD | B29: /Users/mac/Projects/仟流智算/V4/仟流智算-产品需求文档-v2.0.md
A30: 仟流智算 2.0 TRD | B30: /Users/mac/Projects/仟流智算/V4/仟流智算-技术需求文档-v2.0.md
